yu/__init__.py
yu/logo.py
yu/yu.py
yusssstd-1.7.dist-info/METADATA
yusssstd-1.7.dist-info/RECORD
yusssstd-1.7.dist-info/WHEEL
yusssstd-1.7.dist-info/top_level.txt
