Metadata-Version: 2.1
Name: yusssstd
Version: 1.7
Summary: person
Home-page: UNKNOWN
Author: yuan
Author-email: 3089328436@qq.com
License: UNKNOWN
Platform: all
